LICENSE.md
MANIFEST.in
README.md
setup.cfg
setup.py
django_widgets/__init__.py
django_widgets/api.py
django_widgets/apps.py
django_widgets/middleware.py
django_widgets/mixin.py
django_widgets/renderers.py
django_widgets/storage.py
django_widgets/widget.py
django_widgets/__pycache__/__init__.cpython-38.pyc
django_widgets/__pycache__/api.cpython-38.pyc
django_widgets/__pycache__/middleware.cpython-38.pyc
django_widgets/__pycache__/mixin.cpython-38.pyc
django_widgets/__pycache__/renderers.cpython-38.pyc
django_widgets/__pycache__/storage.cpython-38.pyc
django_widgets/__pycache__/widget.cpython-38.pyc
django_widgets/jinja2/django_widgets/widgets/attrs.html
django_widgets/jinja2tags/__init__.py
django_widgets/jinja2tags/widget.py
django_widgets/jinja2tags/__pycache__/__init__.cpython-38.pyc
django_widgets/jinja2tags/__pycache__/widget.cpython-38.pyc
django_widgets/templates/django_widgets/widgets/attrs.html
django_widgets/templatetags/__init__.py
django_widgets/templatetags/widget.py
django_widgets/templatetags/__pycache__/__init__.cpython-38.pyc
django_widgets/templatetags/__pycache__/widget.cpython-38.pyc
django_widgets_engine.egg-info/PKG-INFO
django_widgets_engine.egg-info/SOURCES.txt
django_widgets_engine.egg-info/dependency_links.txt
django_widgets_engine.egg-info/requires.txt
django_widgets_engine.egg-info/top_level.txt