Metadata-Version: 2.1
Name: django-widgets-engine
Version: 1.0.1
Summary: Custom widgets for Django templates
Home-page: https://github.com/LeonLegion/django-widgets
Author: Leonid Evstigneev
Author-email: mail@leonidevstigneev.ru
License: BSD
Keywords: django widget template jinja2
Platform: UNKNOWN
Classifier: Development Status :: 5 - Production/Stable
Classifier: Framework :: Django
Classifier: Intended Audience :: Developers
Classifier: Programming Language :: Python
Classifier: Programming Language :: Python :: 3
Classifier: Topic :: Software Development :: Libraries :: Python Modules
